sammi/__init__.py
sammi/browser/demo.json
sammi/browser/helpfunctions.js
sammi/browser/index.html
sammi/browser/index_load.html
sammi/browser/sammi.css
sammi/browser/simulationfunctions.js
sammi/browser/uploaddownload.js
sammi-0.1.7.dist-info/LICENSE
sammi-0.1.7.dist-info/METADATA
sammi-0.1.7.dist-info/WHEEL
sammi-0.1.7.dist-info/top_level.txt
sammi-0.1.7.dist-info/RECORD
