Metadata-Version: 2.1
Name: sammi
Version: 0.1.7
Summary: A wrapper for running the Semi-Automated Metabolic Map Illustrator (SAMMI) using Python
Home-page: https://github.com/schultzdre/SAMMIpy.git
Author: Andre Schultz
Author-email: schultzdre@gmail.com
License: UNKNOWN
Platform: UNKNOWN
Classifier: Programming Language :: Python :: 3
Classifier: License :: OSI Approved :: MIT License
Classifier: Operating System :: OS Independent
Requires-Dist: cobra
Requires-Dist: numpy
